noseyparker_explorer/__init__.py
noseyparker_explorer/app.py
noseyparker_explorer/comment_screen.py
noseyparker_explorer/datastore.py
noseyparker_explorer/facets.py
noseyparker_explorer/facets_tree.py
noseyparker_explorer/filters.py
noseyparker_explorer/finding_details.py
noseyparker_explorer/findings.py
noseyparker_explorer/findings_table.py
noseyparker_explorer/help.py
noseyparker_explorer/main.py
noseyparker_explorer/match_source_screen.py
noseyparker_explorer/noseyparker_explorer.tcss
noseyparker_explorer/py.typed
noseyparker_explorer/scroll.py
noseyparker_explorer/timed.py
noseyparker_explorer/vi_motion.py
noseyparker_explorer-0.24.0.dist-info/METADATA
noseyparker_explorer-0.24.0.dist-info/WHEEL
noseyparker_explorer-0.24.0.dist-info/entry_points.txt
noseyparker_explorer-0.24.0.dist-info/top_level.txt
noseyparker_explorer-0.24.0.dist-info/RECORD
