Metadata-Version: 2.4
Name: noseyparker-explorer
Version: 0.24.0
Summary: Interactive results explorer and annotator for Nosey Parker
Author-email: Brad Larsen <bradford.larsen@praetorian.com>
Project-URL: Repository, https://github.com/praetorian-inc/noseyparkerexplorer
Project-URL: Issues, https://github.com/praetorian-inc/noseyparkerexplorer/issues
Project-URL: Changelog, https://github.com/praetorian-inc/noseyparkerexplorer/blob/main/CHANGELOG.md
Classifier: Development Status :: 4 - Beta
Classifier: License :: OSI Approved :: Apache Software License
Classifier: Programming Language :: Python
Classifier: Programming Language :: Python :: 3
Classifier: Programming Language :: Python :: 3.10
Classifier: Programming Language :: Python :: 3.11
Classifier: Programming Language :: Python :: 3.12
Classifier: Programming Language :: Python :: 3.13
Classifier: Environment :: Console
Classifier: Intended Audience :: Information Technology
Classifier: Intended Audience :: Developers
Classifier: Topic :: Security
Requires-Python: >=3.10
Requires-Dist: aiosqlite>=0.21.0
Requires-Dist: duckdb>=1.2.2
Requires-Dist: filelock>=3.18.0
Requires-Dist: rich>=14.0.0
Requires-Dist: textual>=3.2.0
